sklearn_genetic/__init__.py
sklearn_genetic/_version.py
sklearn_genetic/algorithms.py
sklearn_genetic/genetic_search.py
sklearn_genetic/mlflow_log.py
sklearn_genetic/parameters.py
sklearn_genetic/plots.py
sklearn_genetic/callbacks/__init__.py
sklearn_genetic/callbacks/base.py
sklearn_genetic/callbacks/early_stoppers.py
sklearn_genetic/callbacks/loggers.py
sklearn_genetic/callbacks/model_checkpoint.py
sklearn_genetic/callbacks/validations.py
sklearn_genetic/schedules/__init__.py
sklearn_genetic/schedules/base.py
sklearn_genetic/schedules/schedulers.py
sklearn_genetic/schedules/validations.py
sklearn_genetic/space/__init__.py
sklearn_genetic/space/base.py
sklearn_genetic/space/space.py
sklearn_genetic/space/space_parameters.py
sklearn_genetic/utils/__init__.py
sklearn_genetic/utils/cv_scores.py
sklearn_genetic/utils/logbook.py
sklearn_genetic/utils/random.py
sklearn_genetic/utils/tools.py
sklearn_genetic_opt-0.12.0.dist-info/LICENSE
sklearn_genetic_opt-0.12.0.dist-info/METADATA
sklearn_genetic_opt-0.12.0.dist-info/WHEEL
sklearn_genetic_opt-0.12.0.dist-info/top_level.txt
sklearn_genetic_opt-0.12.0.dist-info/RECORD
