Metadata-Version: 2.1
Name: sklearn-genetic-opt
Version: 0.12.0
Summary: Scikit-learn models hyperparameters tuning and features selection, using evolutionary algorithms
Home-page: https://github.com/rodrigo-arenas/Sklearn-genetic-opt
Author: Rodrigo Arenas
Author-email: rodrigo.arenas456@gmail.com
License: MIT
Project-URL: Documentation, https://sklearn-genetic-opt.readthedocs.io/en/stable/
Project-URL: Source Code, https://github.com/rodrigo-arenas/Sklearn-genetic-opt
Project-URL: Bug Tracker, https://github.com/rodrigo-arenas/Sklearn-genetic-opt/issues
Classifier: License :: OSI Approved :: MIT License
Classifier: Programming Language :: Python :: 3
Classifier: Programming Language :: Python :: 3.9
Classifier: Programming Language :: Python :: 3.10
Classifier: Programming Language :: Python :: 3.11
Classifier: Programming Language :: Python :: 3.12
Requires-Python: >=3.9
License-File: LICENSE
Requires-Dist: scikit-learn >=1.5.0
Requires-Dist: numpy >=1.26.1
Requires-Dist: deap >=1.3.3
Requires-Dist: tqdm >=4.61.1
Provides-Extra: all
Requires-Dist: mlflow >=2.20.0 ; extra == 'all'
Requires-Dist: seaborn >=0.11.2 ; extra == 'all'
Requires-Dist: tensorflow >=2.17.1 ; extra == 'all'
Provides-Extra: mlflow
Requires-Dist: mlflow >=2.20.0 ; extra == 'mlflow'
Provides-Extra: seaborn
Requires-Dist: seaborn >=0.11.2 ; extra == 'seaborn'
Provides-Extra: tensorflow
Requires-Dist: tensorflow >=2.17.1 ; extra == 'tensorflow'
